empower/__init__.py
empower/_core.py
empower/_trait.py
empower_py-0.1.0.dist-info/LICENSE
empower_py-0.1.0.dist-info/WHEEL
empower_py-0.1.0.dist-info/METADATA
empower_py-0.1.0.dist-info/RECORD
