Metadata-Version: 2.1
Name: empower-py
Version: 0.1.0
Summary: Goodbye Inheritance
License: Apache-2.0
Author: ZhengYu, Xu
Author-email: zen-xu@outlook.com
Requires-Python: >=3.6,<4.0
Classifier: License :: OSI Approved :: Apache Software License
Classifier: Programming Language :: Python :: 3
Classifier: Programming Language :: Python :: 3.10
Classifier: Programming Language :: Python :: 3.6
Classifier: Programming Language :: Python :: 3.7
Classifier: Programming Language :: Python :: 3.8
Classifier: Programming Language :: Python :: 3.9
Requires-Dist: wrapt (>=1.11,<2.0)
